Metadata-Version: 2.1
Name: testasasnkaonlytest
Version: 0.1.2
Summary: A very basic calculator
Home-page: UNKNOWN
Author: Joshua Lowe
Author-email: wassoftasanka@gmail.com
License: MIT
Keywords: calculator
Platform: UNKNOWN
Classifier: Development Status :: 5 - Production/Stable
Classifier: Intended Audience :: Education
Classifier: Operating System :: Microsoft :: Windows :: Windows 10
Classifier: License :: OSI Approved :: MIT License
Classifier: Programming Language :: Python :: 3
